[
    {
      "id":1,
      "Gen": "2023-22-03-092254",
      "Game": "S1",
      "N": {
        "hand": "87.J863.AT2.6432",
        "hcp": 5,
        "bergen_adj3": 5.5
      },
      "E": {
        "hand": "543.754.QJ98.AK8",
        "hcp": 10,
        "bergen_adj3": 9.75
      },
      "S": {
        "hand": "KJ9.AKQ2.K54.J95",
        "hcp": 17,
        "bergen_adj3": 16.5
      },
      "W": {
        "hand": "AQT62.T9.763.QT7",
        "hcp": 8,
        "bergen_adj3": 8.25
      }
    },
    {
      "id":2,
      "Gen": "2023-22-03-092254",
      "Game": "S2",
      "N": {
        "hand": "87.J863.AT2.6432",
        "hcp": 5,
        "bergen_adj3": 5.5
      },
      "E": {
        "hand": "543.754.QJ98.AK8",
        "hcp": 10,
        "bergen_adj3": 9.75
      },
      "S": {
        "hand": "KJ9.AKQ2.K54.J95",
        "hcp": 17,
        "bergen_adj3": 16.5
      },
      "W": {
        "hand": "AQT62.T9.763.QT7",
        "hcp": 8,
        "bergen_adj3": 8.25
      }
    }
]
